pav3/__init__.py
pav3/__main__.py
pav3/anno.py
pav3/const.py
pav3/inv.py
pav3/io.py
pav3/kde.py
pav3/params.py
pav3/pipeline.py
pav3/region.py
pav3/schema.py
pav3/seq.py
pav3/util.py
pav3/vcf.py
pav3/align/__init__.py
pav3/align/features.py
pav3/align/lift.py
pav3/align/op.py
pav3/align/records.py
pav3/align/score.py
pav3/align/tables.py
pav3/align/trim.py
pav3/align/lcmodel/__init__.py
pav3/align/lcmodel/_lcmodel.py
pav3/align/lcmodel/_lcmodel_logistic.py
pav3/align/lcmodel/_lcmodel_null.py
pav3/align/lcmodel/_util.py
pav3/call/__init__.py
pav3/call/expr.py
pav3/call/integrate.py
pav3/call/intra.py
pav3/call/util.py
pav3/cli/__init__.py
pav3/cli/_cli.py
pav3/cli/_common_opt.py
pav3/cli/_subcommand_batch.py
pav3/cli/_subcommand_call.py
pav3/cli/_subcommand_license.py
pav3/data/lcmodel/default/model.json
pav3/data/lcmodel/human_95_80/model.json
pav3/data/lcmodel/human_95_80/model_info.tar.gz
pav3/data/lcmodel/human_95_80/weights.npz
pav3/data/lcmodel/human_98_80/model.json
pav3/data/lcmodel/human_98_80/model_info.tar.gz
pav3/data/lcmodel/human_98_80/weights.npz
pav3/data/lcmodel/prim_90_50/model.json
pav3/data/lcmodel/prim_90_50/model_info.tar.gz
pav3/data/lcmodel/prim_90_50/weights.npz
pav3/data/lcmodel/primdiv_85_50/model.json
pav3/data/lcmodel/primdiv_85_50/model_info.tar.gz
pav3/data/lcmodel/primdiv_85_50/weights.npz
pav3/data/workflow/Snakefile
pav3/data/workflow/profiles/pav_default/config.yaml
pav3/data/workflow/rules/align.smk
pav3/data/workflow/rules/call.smk
pav3/data/workflow/rules/data.smk
pav3/data/workflow/rules/pipeline.smk
pav3/dev/__init__.py
pav3/dev/imports.py
pav3/dev/sm.py
pav3/dev/tables.py
pav3/lgsv/__init__.py
pav3/lgsv/call.py
pav3/lgsv/chain.py
pav3/lgsv/interval.py
pav3/lgsv/io.py
pav3/lgsv/region_kde.py
pav3/lgsv/resources.py
pav3/lgsv/struct.py
pav3/lgsv/variant.py
pav3-3.0.0.dev14.dist-info/licenses/LICENSE
pav3-3.0.0.dev14.dist-info/METADATA
pav3-3.0.0.dev14.dist-info/WHEEL
pav3-3.0.0.dev14.dist-info/entry_points.txt
pav3-3.0.0.dev14.dist-info/top_level.txt
pav3-3.0.0.dev14.dist-info/RECORD
