Metadata-Version: 2.4
Name: pav3
Version: 3.0.0.dev14
Summary: Assembly-based variant discovery
License-Expression: MIT
Requires-Python: >=3.12
License-File: LICENSE
Requires-Dist: agglovar>=0.0.1.dev8
Requires-Dist: biopython>=1.85
Requires-Dist: fastexcel>=0.14.0
Requires-Dist: frozendict>=2.4.6
Requires-Dist: intervaltree>=3.1.0
Requires-Dist: numpy>=2.3.2
Requires-Dist: polars[numpy,pandas,pyarrow]>=1.35.2
Requires-Dist: pyarrow>=21.0.0
Requires-Dist: pysam>=0.23.3
Requires-Dist: scipy>=1.16.1
Requires-Dist: scipy-stubs==1.16.1.1
Requires-Dist: snakemake>=9.9.0
Dynamic: license-file
